converter_machine-1.0.2.dist-info/licenses/LICENSE
test/__init__.py
test/test_area.py
test/test_data.py
test/test_length.py
test/test_mass.py
test/test_speed.py
test/test_temperature.py
test/test_time.py
test/test_volume.py
converter_machine-1.0.2.dist-info/METADATA
converter_machine-1.0.2.dist-info/WHEEL
converter_machine-1.0.2.dist-info/top_level.txt
converter_machine-1.0.2.dist-info/RECORD
