Metadata-Version: 2.4
Name: Converter_machine
Version: 1.0.2
Summary: A unit conversion library for time, mass, length, temperature, and more
Home-page: https://github.com/AmirKimiaei/converter_machine
Author: Amir M. Kimiaei
Author-email: a.m.kimiaei84@email.com
Classifier: Programming Language :: Python :: 3
Classifier: License :: OSI Approved :: MIT License
Classifier: Operating System :: OS Independent
License-File: LICENSE
Dynamic: author
Dynamic: author-email
Dynamic: classifier
Dynamic: description
Dynamic: description-content-type
Dynamic: home-page
Dynamic: license-file
Dynamic: summary
